resultr/__init__.py
resultr/__main__.py
resultr/command_line.py
resultr-0.1.10.dist-info/METADATA
resultr-0.1.10.dist-info/RECORD
resultr-0.1.10.dist-info/WHEEL
resultr-0.1.10.dist-info/entry_points.txt
resultr-0.1.10.dist-info/top_level.txt
